src/alu_control.v
module alu_control (
    instruction,
    ALUOp,
    ALUcontrol
);
  input [31:0] instruction;
  input [1:0] ALUOp;
  wire [2:0] func3;
  output  reg [2:0] ALUcontrol;
  wire funct7_5;
  assign funct7_5 = instruction[30];
  assign func3 = instruction[14:12];
  always @(*) begin
    ALUcontrol = 3'b000;
    case (ALUOp)
      2'b00: begin
        ALUcontrol = 3'b000;
      end
      2'b01: begin
        ALUcontrol = 3'b001;
      end
      2'b10: begin
        if (func3 == 3'b000) begin
          if (funct7_5 == 1'b0) ALUcontrol = 3'b000;
          else ALUcontrol = 3'b001;
        end else if (func3 == 3'b110) ALUcontrol = 3'b011;
        else if (func3 == 3'b111) ALUcontrol = 3'b010;
        else if (func3 == 3'b010) ALUcontrol = 3'b101;
      end
    endcase
  end
endmodule

src/control_unit.v
module control_unit (
    instruction,
    RegWrite,
    ALUSrc,
    MemWrite,
    MemRead,
    MemToReg,
    Branch,
    Jump,
    ALUOp
);
  input [31:0] instruction;
  output reg RegWrite, ALUSrc, MemWrite, MemRead;
  output reg MemToReg, Branch, Jump;
  output reg [1:0] ALUOp;
  always @(*) begin
    RegWrite = 0;
    ALUSrc   = 0;
    MemWrite = 0;
    MemRead  = 0;
    MemToReg = 0;
    Branch   = 0;
    Jump     = 0;
    ALUOp    = 2'b00;
    case (instruction[6:0])
      7'b0000011: begin
        MemToReg = 1;
        MemRead = 1;
        RegWrite = 1;
        ALUSrc = 1;
        ALUOp = 2'b00;
      end  //lw
      7'b0100011: begin
        MemWrite = 1;
        ALUSrc = 1;
        ALUOp = 2'b00;
      end  //sw
      7'b0110011: begin
        RegWrite = 1;
        ALUOp = 2'b10;
      end  //add
      7'b0010011: begin
        RegWrite = 1;
        ALUSrc = 1;
        ALUOp = 2'b00;
      end  //addi
      7'b1100011: begin
        ALUOp  = 2'b01;
        Branch = 1;
      end  //branch
      7'b1101111: begin
        RegWrite = 1;
        Jump = 1;
      end  //jal
      7'b0110111: begin
        RegWrite = 1;
        ALUSrc = 1;
        ALUOp = 2'b11;
      end  //lui


      default: begin
        RegWrite = 0;
        ALUSrc = 0;
        MemWrite = 0;
        MemRead = 0;
        MemToReg = 0;
        Branch = 0;
        Jump = 0;
        ALUOp = 2'b00;
      end


    endcase
  end
endmodule

src/alu.v
module alu(a, b , ALUcontrol ,result, carry,zero,negative,overflow,slt);
input [31:0]a,b;
input [2:0]ALUcontrol;
output [31:0]result,zero,slt;
output carry,negative,overflow;
wire [31:0]a_and_b,a_or_b,not_b,wire_b,sum;
wire cout,xnor_gate,xor_gate;
assign a_and_b = a & b;
assign a_or_b = a | b ;
assign not_b = ~b;
assign wire_b = (ALUcontrol[0] == 1'b0) ? b :not_b;
assign {cout,sum} = a + wire_b + ALUcontrol[0];
assign slt = {31'b0000000000000000000000000000000,sum[31]};
assign result = (ALUcontrol[2:0] == 3'b000) ? sum:
                (ALUcontrol[2:0] == 3'b001) ? sum:
                (ALUcontrol[2:0] == 3'b010) ? a_and_b:
                 (ALUcontrol[2:0] == 3'b011) ? a_or_b:
                 (ALUcontrol[2:0] == 3'b101) ? slt: 32'h00000000;
assign carry = ~ALUcontrol[1] & cout;
assign zero = &(~result);
assign negative = result[31];
assign xor_gate = (a[31] ^ sum[31]);
assign xnor_gate = ~(a[31] ^ ALUcontrol[0] ^ b[31]);
assign overflow = xnor_gate & xor_gate & (~ALUcontrol[1]);


endmodule

src/data_memory.v
module data_memory(clk,we,address,data_in,data_out);
input clk,we;
input [31:0]address,data_in;
output [31:0]data_out;
reg [31:0] regs [1023:0];
always @(posedge clk) 
if (we==1 ) begin regs[address[11:2]]<=data_in;
end
assign data_out = regs[address[11:2]];
endmodule

src/register_file.v
module register_file(we,rs1_addr,rs2_addr,clk,rd_addr,rs1_data,rs2_data,rd_data);
input [4:0]rs1_addr,rs2_addr,rd_addr;
output [31:0]rs1_data,rs2_data;
reg [31:0] regs [0:31];
input clk,we;
input [31:0] rd_data;
assign rs1_data = regs[rs1_addr];
assign rs2_data = regs[rs2_addr];
integer i;
initial begin
    for (i = 0; i < 32; i = i + 1)
        regs[i] = 32'b0;
end
always @(posedge clk) begin
    if(we && rd_addr != 5'b0)begin
        regs[rd_addr]<=rd_data;
end
end
endmodule

src/imm_gen.v
module imm_gen (
    instruction,
    imm_out
);
  input [31:0] instruction;
  output reg [31:0] imm_out;
  always @(*)
    case (instruction[6:0])
      7'b0010011, 7'b0000011: imm_out = {{20{instruction[31]}}, instruction[31:20]};  //I-type
      7'b0100011:
      imm_out = {{20{instruction[31]}}, instruction[31:25], instruction[11:7]};  //S-type
      7'b0110111, 7'b0010111: imm_out = {instruction[31:12], 12'b0};  //U-type
      7'b1101111:
      imm_out = {
        {11{instruction[31]}},
        instruction[31],
        instruction[19:12],
        instruction[20],
        instruction[30:21],
        1'b0
      };  //J-type
      7'b1100011:
      imm_out = {
        {19{instruction[31]}},
        instruction[31],
        instruction[7],
        instruction[30:25],
        instruction[11:8],
        1'b0
      };  //B-type
      default: imm_out = 32'b0;
    endcase
endmodule

src/instr_mem.v
module instr_mem (
    addr,
    instruction
);
  input [31:0] addr;
  output [31:0] instruction;
  reg [31:0] mem[1023:0];
  initial $readmemh("src/program.hex", mem);
  assign instruction = mem[addr[11:2]];
endmodule

src/top_unit.v
`include "src/instr_mem.v"
`include "src/imm_gen.v"
`include "src/register_file.v"
`include "src/data_memory.v"
`include "src/alu.v"
`include "src/control_unit.v"
`include "src/alu_control.v"
module top_unit(clk,reset);
input clk;
input reset;
reg [31:0] pc;
wire [31:0]rd_data,rs2_data,rs1_data,imm_out,result,data_out,pc_next,alu_b,instruction,zero,slt;
wire ALUSrc,MemToReg,MemWrite,MemRead,Branch,Jump,RegWrite;
wire [1:0]ALUOp;
wire [2:0]ALUcontrol;
assign alu_b = ALUSrc ? imm_out :rs2_data;
assign rd_data = MemToReg ? data_out : result;
assign pc_next = Jump ? pc+imm_out : 
(Branch & zero) ? pc + imm_out:
pc + 4;
always @(posedge clk) begin
    if(reset)
    pc<= 32'b0;
    else
    pc<= pc_next;
end
instr_mem instr_mem(
    .addr(pc),
    .instruction(instruction)
);
imm_gen imm_gen(
    .instruction(instruction),
    .imm_out(imm_out)
);
register_file register_file(
    .we(RegWrite),
    .clk(clk),
    .rd_addr(instruction[11:7]),
    .rs1_addr(instruction[19:15]),
    .rs2_addr(instruction[24:20]),
    .rd_data(rd_data),
    .rs1_data(rs1_data),
    .rs2_data(rs2_data)
);
data_memory data_memory(
.clk(clk),
.we(MemWrite),
.data_in(result),
.data_out(data_out),
.address(result)
);
alu alu(
.a(rs1_data),
.b(alu_b),
.result(result),
.slt(slt),
.ALUcontrol(ALUcontrol),
.zero(zero)
);
control_unit control_unit(
.instruction(instruction),
.RegWrite(RegWrite),
.ALUSrc(ALUSrc),
.MemWrite(MemWrite),
.MemRead(MemRead),
.MemToReg(MemToReg),
.Branch(Branch),
.Jump(Jump),
.ALUOp(ALUOp)
);
alu_control alu_control(
    .instruction(instruction),
    .ALUOp(ALUOp),
    .ALUcontrol(ALUcontrol)

);

endmodule

testbenches/top_unit_test.v
module top_unit_test();
reg reset,clk;

top_unit uut(
    .reset(reset),
    .clk(clk)
);
initial begin
    $dumpfile("top_unit.vcd");
    $dumpvars(0,top_unit_test);
    clk=0;
end
always
begin clk = ~clk;
#10;
end 
initial begin
    reset<=1'b1;
    #50;
    reset<=1'b0;
    #500;
    $finish;
end
endmodule

top_unit.vcd
$date
	Fri Jul  3 15:49:08 2026
$end
$version
	Icarus Verilog
$end
$timescale
	1s
$end
$scope module top_unit_test $end
$var reg 1 ! clk $end
$var reg 1 " reset $end
$scope module uut $end
$var wire 1 ! clk $end
$var wire 1 " reset $end
$var wire 32 # zero [31:0] $end
$var wire 32 $ slt [31:0] $end
$var wire 32 % rs2_data [31:0] $end
$var wire 32 & rs1_data [31:0] $end
$var wire 32 ' result [31:0] $end
$var wire 32 ( rd_data [31:0] $end
$var wire 32 ) pc_next [31:0] $end
$var wire 32 * instruction [31:0] $end
$var wire 32 + imm_out [31:0] $end
$var wire 32 , data_out [31:0] $end
$var wire 32 - alu_b [31:0] $end
$var wire 1 . RegWrite $end
$var wire 1 / MemWrite $end
$var wire 1 0 MemToReg $end
$var wire 1 1 MemRead $end
$var wire 1 2 Jump $end
$var wire 1 3 Branch $end
$var wire 3 4 ALUcontrol [2:0] $end
$var wire 1 5 ALUSrc $end
$var wire 2 6 ALUOp [1:0] $end
$var reg 32 7 pc [31:0] $end
$scope module alu $end
$var wire 32 8 a_and_b [31:0] $end
$var wire 32 9 a_or_b [31:0] $end
$var wire 32 : b [31:0] $end
$var wire 1 ; carry $end
$var wire 32 < not_b [31:0] $end
$var wire 1 = overflow $end
$var wire 1 > xnor_gate $end
$var wire 1 ? xor_gate $end
$var wire 32 @ zero [31:0] $end
$var wire 32 A wire_b [31:0] $end
$var wire 32 B sum [31:0] $end
$var wire 32 C slt [31:0] $end
$var wire 32 D result [31:0] $end
$var wire 1 E negative $end
$var wire 1 F cout $end
$var wire 32 G a [31:0] $end
$var wire 3 H ALUcontrol [2:0] $end
$upscope $end
$scope module alu_control $end
$var wire 32 I instruction [31:0] $end
$var wire 1 J funct7_5 $end
$var wire 3 K func3 [2:0] $end
$var wire 2 L ALUOp [1:0] $end
$var reg 3 M ALUcontrol [2:0] $end
$upscope $end
$scope module control_unit $end
$var wire 32 N instruction [31:0] $end
$var reg 2 O ALUOp [1:0] $end
$var reg 1 5 ALUSrc $end
$var reg 1 3 Branch $end
$var reg 1 2 Jump $end
$var reg 1 1 MemRead $end
$var reg 1 0 MemToReg $end
$var reg 1 / MemWrite $end
$var reg 1 . RegWrite $end
$upscope $end
$scope module data_memory $end
$var wire 32 P address [31:0] $end
$var wire 1 ! clk $end
$var wire 32 Q data_in [31:0] $end
$var wire 32 R data_out [31:0] $end
$var wire 1 / we $end
$upscope $end
$scope module imm_gen $end
$var wire 32 S instruction [31:0] $end
$var reg 32 T imm_out [31:0] $end
$upscope $end
$scope module instr_mem $end
$var wire 32 U addr [31:0] $end
$var wire 32 V instruction [31:0] $end
$upscope $end
$scope module register_file $end
$var wire 1 ! clk $end
$var wire 5 W rd_addr [4:0] $end
$var wire 32 X rd_data [31:0] $end
$var wire 5 Y rs1_addr [4:0] $end
$var wire 32 Z rs1_data [31:0] $end
$var wire 5 [ rs2_addr [4:0] $end
$var wire 32 \ rs2_data [31:0] $end
$var wire 1 . we $end
$var integer 32 ] i [31:0] $end
$upscope $end
$upscope $end
$upscope $end
$enddefinitions $end
$comment Show the parameter values. $end
$dumpall
$end
#0
$dumpvars
b100000 ]
bx \
bx [
bx Z
bx Y
bx X
bx W
bx V
bx U
bx T
bx S
bx R
bx Q
bx P
bx O
bx N
bx M
bx L
bx K
xJ
bx I
bx H
bx G
xF
xE
bx D
b0x C
bx B
bx A
b0x @
x?
x>
x=
bx <
x;
bx :
bx 9
bx 8
bx 7
bx 6
x5
bx 4
x3
x2
x1
x0
x/
x.
bx -
bx ,
bx +
bx *
bx )
bx (
bx '
bx &
bx %
b0x $
b0x #
1"
1!
$end
#10
0!
#20
0=
b0 #
b0 @
b0 $
b0 C
0E
b101 (
b101 X
0?
b101 '
b101 D
b101 P
b101 Q
0;
b101 B
0F
1>
b101 A
b100 )
b0 8
b101 9
b11111111111111111111111111111010 <
b0 %
b0 \
b0 &
b0 G
b0 Z
b0 4
b0 H
b0 M
b101 -
b101 :
b0 K
0J
b1 W
b101 [
b0 Y
b0 6
b0 L
b0 O
02
03
00
01
0/
15
1.
b101 +
b101 T
b10100000000000010010011 *
b10100000000000010010011 I
b10100000000000010010011 N
b10100000000000010010011 S
b10100000000000010010011 V
b0 7
b0 U
1!
#30
0!
#40
1!
#50
0"
0!
#60
b1010 (
b1010 X
b1010 '
b1010 D
b1010 P
b1010 Q
b1010 B
b1010 9
b11111111111111111111111111110101 <
b1010 A
b1010 -
b1010 :
b10 W
b1010 [
b1010 +
b1010 T
15
1.
b1000 )
b101000000000000100010011 *
b101000000000000100010011 I
b101000000000000100010011 N
b101000000000000100010011 S
b101000000000000100010011 V
b100 7
b100 U
1!
#70
0!
#80
b1111 (
b1111 X
b1111 '
b1111 D
b1111 P
b1111 Q
b1111 B
b1111 9
b11111111111111111111111111110101 <
b1010 A
b1010 %
b1010 \
b101 &
b101 G
b101 Z
b1010 -
b1010 :
b11 W
b10 [
b1 Y
b10 6
b10 L
b10 O
05
1.
b0 +
b0 T
b1100 )
b1000001000000110110011 *
b1000001000000110110011 I
b1000001000000110110011 N
b1000001000000110110011 S
b1000001000000110110011 V
b1000 7
b1000 U
1!
#90
0!
#100
b1 #
b1 @
b0 (
b0 X
b0 '
b0 D
b0 P
b0 Q
b0 B
b0 9
b11111111111111111111111111111111 <
b0 A
b1111 %
b1111 \
b0 &
b0 G
b0 Z
b0 -
b0 :
b10 K
b0 W
b11 [
b0 Y
15
1/
b0 6
b0 L
b0 O
0.
b10000 )
b1100000010000000100011 *
b1100000010000000100011 I
b1100000010000000100011 N
b1100000010000000100011 S
b1100000010000000100011 V
b1100 7
b1100 U
1!
#110
0!
#120
b0 %
b0 \
b100 W
b0 [
1.
11
10
0/
15
b10100 )
b10001000000011 *
b10001000000011 I
b10001000000011 N
b10001000000011 S
b10001000000011 V
b0 ,
b0 R
b10000 7
b10000 U
1!
#130
0!
#140
bx ,
bx R
1E
b1 $
b1 C
1?
b0 #
b0 @
b11111111111111111111111111110001 (
b11111111111111111111111111110001 X
0;
b11111111111111111111111111110001 '
b11111111111111111111111111110001 D
b11111111111111111111111111110001 P
b11111111111111111111111111110001 Q
0F
0>
b11111111111111111111111111110001 B
b1111 9
b11111111111111111111111111110000 <
b11111111111111111111111111110000 A
b1111 -
b1111 :
b1111 %
b1111 \
b1 4
b1 H
b1 M
b0 K
b1000 W
b11 [
b100 Y
b1000 +
b1000 T
13
b1 6
b1 L
b1 O
00
01
05
0.
b11000 )
b1100100000010001100011 *
b1100100000010001100011 I
b1100100000010001100011 N
b1100100000010001100011 S
b1100100000010001100011 V
b10100 7
b10100 U
1!
#150
0!
#160
b0 ,
b0 R
b0 $
b0 C
0E
0?
0=
b1 (
b1 X
1>
b1 '
b1 D
b1 P
b1 Q
b1 B
b1 A
b1 9
b11111111111111111111111111111110 <
b101 %
b101 \
b1 -
b1 :
b0 4
b0 H
b0 M
b101 W
b1 [
b0 Y
15
1.
b0 6
b0 L
b0 O
03
b1 +
b1 T
b11100 )
b100000000001010010011 *
b100000000001010010011 I
b100000000001010010011 N
b100000000001010010011 S
b100000000001010010011 V
b11000 7
b11000 U
1!
#170
0!
#180
b1 #
b1 @
b0 ,
b0 R
b0 (
b0 X
b0 '
b0 D
b0 P
b0 Q
b0 B
b0 9
b11111111111111111111111111111111 <
b0 A
b0 %
b0 \
b0 -
b0 :
b0 W
b0 [
b0 +
b0 T
12
05
1.
b11100 )
b1101111 *
b1101111 I
b1101111 N
b1101111 S
b1101111 V
b11100 7
b11100 U
1!
